reportity/__init__.py
reportity/reportity.py
reportity-1.23.3.dist-info/LICENSE.txt
reportity-1.23.3.dist-info/METADATA
reportity-1.23.3.dist-info/WHEEL
reportity-1.23.3.dist-info/top_level.txt
reportity-1.23.3.dist-info/RECORD
